drawlib/__init__.py
drawlib/__main__.py
drawlib/apis.py
drawlib/assets/__init__.py
drawlib/assets/v0_2/__init__.py
drawlib/assets/v0_2/fonticons/__init__.py
drawlib/assets/v0_2/fonts/__init__.py
drawlib/py.typed
drawlib/v0_2/__init__.py
drawlib/v0_2/__main__.py
drawlib/v0_2/apis.py
drawlib/v0_2/private/__init__.py
drawlib/v0_2/private/command.py
drawlib/v0_2/private/core/__init__.py
drawlib/v0_2/private/core/colors.py
drawlib/v0_2/private/core/dimage.py
drawlib/v0_2/private/core/fonts.py
drawlib/v0_2/private/core/model.py
drawlib/v0_2/private/core/model_system_default.py
drawlib/v0_2/private/core/theme.py
drawlib/v0_2/private/core/theme_officials.py
drawlib/v0_2/private/core/theme_style_caches.py
drawlib/v0_2/private/core/util.py
drawlib/v0_2/private/core_canvas/__init__.py
drawlib/v0_2/private/core_canvas/base.py
drawlib/v0_2/private/core_canvas/canvas.py
drawlib/v0_2/private/core_canvas/image.py
drawlib/v0_2/private/core_canvas/line.py
drawlib/v0_2/private/core_canvas/original_arrow.py
drawlib/v0_2/private/core_canvas/original_polygon.py
drawlib/v0_2/private/core_canvas/patches.py
drawlib/v0_2/private/core_canvas/text.py
drawlib/v0_2/private/download.py
drawlib/v0_2/private/dutil/__init__.py
drawlib/v0_2/private/dutil/dutil_canvas.py
drawlib/v0_2/private/dutil/dutil_color.py
drawlib/v0_2/private/dutil/dutil_script.py
drawlib/v0_2/private/dutil/settings.py
drawlib/v0_2/private/icons/__init__.py
drawlib/v0_2/private/icons/phosphor.py
drawlib/v0_2/private/icons/util.py
drawlib/v0_2/private/logging.py
drawlib/v0_2/private/smartarts/__init__.py
drawlib/v0_2/private/smartarts/boxlist.py
drawlib/v0_2/private/smartarts/boxtree.py
drawlib/v0_2/private/smartarts/bubblespeech.py
drawlib/v0_2/private/smartarts/bulletpoints.py
drawlib/v0_2/private/smartarts/dsart.py
drawlib/v0_2/private/smartarts/gridlayout.py
drawlib/v0_2/private/smartarts/pyramid.py
drawlib/v0_2/private/smartarts/sourcecode.py
drawlib/v0_2/private/smartarts/table.py
drawlib/v0_2/private/smartarts/tree.py
drawlib-0.2.3.dist-info/LICENSE.txt
drawlib-0.2.3.dist-info/METADATA
drawlib-0.2.3.dist-info/WHEEL
drawlib-0.2.3.dist-info/entry_points.txt
drawlib-0.2.3.dist-info/RECORD
