Metadata-Version: 2.1
Name: drawlib
Version: 0.2.3
Summary: Python drawing library. Illustration as Code.
Home-page: https://www.drawlib.com
Author: Yuichi Ito
Author-email: yuichi@yuichi.com
Requires-Python: >=3.9,<4.0
Classifier: Programming Language :: Python :: 3
Classifier: Programming Language :: Python :: 3.9
Classifier: Programming Language :: Python :: 3.10
Classifier: Programming Language :: Python :: 3.11
Classifier: Programming Language :: Python :: 3.12
Requires-Dist: matplotlib (>=3.8.3,<4.0.0)
Requires-Dist: pygments (>=2.17.2,<3.0.0)
Project-URL: Repository, https://github.com/yuichi110/drawlib
